odoo8_addon_l10n_it_fatturapa_out_sale-8.0.2.0.1-nspkg.pth
odoo_addons/l10n_it_fatturapa_out_sale/README.rst
odoo_addons/l10n_it_fatturapa_out_sale/__init__.py
odoo_addons/l10n_it_fatturapa_out_sale/__openerp__.py
odoo_addons/l10n_it_fatturapa_out_sale/i18n/l10n_it_fatturapa_out_sale.pot
odoo_addons/l10n_it_fatturapa_out_sale/models/__init__.py
odoo_addons/l10n_it_fatturapa_out_sale/models/account_invoice.py
odoo_addons/l10n_it_fatturapa_out_sale/models/company.py
odoo_addons/l10n_it_fatturapa_out_sale/models/partner.py
odoo_addons/l10n_it_fatturapa_out_sale/readme/CONTRIBUTORS.rst
odoo_addons/l10n_it_fatturapa_out_sale/readme/DESCRIPTION.rst
odoo_addons/l10n_it_fatturapa_out_sale/static/description/icon.png
odoo_addons/l10n_it_fatturapa_out_sale/static/description/index.html
odoo_addons/l10n_it_fatturapa_out_sale/views/account_view.xml
odoo_addons/l10n_it_fatturapa_out_sale/views/company_view.xml
odoo_addons/l10n_it_fatturapa_out_sale/views/partner_view.xml
odoo_addons/l10n_it_fatturapa_out_sale/wizard/__init__.py
odoo_addons/l10n_it_fatturapa_out_sale/wizard/wizard_export_fatturapa.py
odoo8_addon_l10n_it_fatturapa_out_sale-8.0.2.0.1.dist-info/METADATA
odoo8_addon_l10n_it_fatturapa_out_sale-8.0.2.0.1.dist-info/WHEEL
odoo8_addon_l10n_it_fatturapa_out_sale-8.0.2.0.1.dist-info/namespace_packages.txt
odoo8_addon_l10n_it_fatturapa_out_sale-8.0.2.0.1.dist-info/top_level.txt
odoo8_addon_l10n_it_fatturapa_out_sale-8.0.2.0.1.dist-info/RECORD
